odoo/addons/account_credit_control_dunning_fees/README.rst
odoo/addons/account_credit_control_dunning_fees/__init__.py
odoo/addons/account_credit_control_dunning_fees/__manifest__.py
odoo/addons/account_credit_control_dunning_fees/i18n/account_credit_control_dunning_fees.pot
odoo/addons/account_credit_control_dunning_fees/i18n/am.po
odoo/addons/account_credit_control_dunning_fees/i18n/ar.po
odoo/addons/account_credit_control_dunning_fees/i18n/bg.po
odoo/addons/account_credit_control_dunning_fees/i18n/bs.po
odoo/addons/account_credit_control_dunning_fees/i18n/ca.po
odoo/addons/account_credit_control_dunning_fees/i18n/cs.po
odoo/addons/account_credit_control_dunning_fees/i18n/da.po
odoo/addons/account_credit_control_dunning_fees/i18n/de.po
odoo/addons/account_credit_control_dunning_fees/i18n/el_GR.po
odoo/addons/account_credit_control_dunning_fees/i18n/en_GB.po
odoo/addons/account_credit_control_dunning_fees/i18n/es.po
odoo/addons/account_credit_control_dunning_fees/i18n/es_AR.po
odoo/addons/account_credit_control_dunning_fees/i18n/es_CL.po
odoo/addons/account_credit_control_dunning_fees/i18n/es_CO.po
odoo/addons/account_credit_control_dunning_fees/i18n/es_CR.po
odoo/addons/account_credit_control_dunning_fees/i18n/es_DO.po
odoo/addons/account_credit_control_dunning_fees/i18n/es_EC.po
odoo/addons/account_credit_control_dunning_fees/i18n/es_ES.po
odoo/addons/account_credit_control_dunning_fees/i18n/es_MX.po
odoo/addons/account_credit_control_dunning_fees/i18n/es_PE.po
odoo/addons/account_credit_control_dunning_fees/i18n/es_PY.po
odoo/addons/account_credit_control_dunning_fees/i18n/es_VE.po
odoo/addons/account_credit_control_dunning_fees/i18n/et.po
odoo/addons/account_credit_control_dunning_fees/i18n/eu.po
odoo/addons/account_credit_control_dunning_fees/i18n/fa.po
odoo/addons/account_credit_control_dunning_fees/i18n/fi.po
odoo/addons/account_credit_control_dunning_fees/i18n/fr.po
odoo/addons/account_credit_control_dunning_fees/i18n/fr_CA.po
odoo_addon_account_credit_control_dunning_fees-17.0.1.0.0.3.dist-info/METADATA
odoo_addon_account_credit_control_dunning_fees-17.0.1.0.0.3.dist-info/WHEEL
odoo_addon_account_credit_control_dunning_fees-17.0.1.0.0.3.dist-info/top_level.txt
odoo_addon_account_credit_control_dunning_fees-17.0.1.0.0.3.dist-info/RECORD
